shapely_ext/__init__.py
shapely_ext/angle.py
shapely_ext/decompose.py
shapely_ext/func.py
shapely_ext/interpolate.py
shapely_ext/mesh.py
shapely_ext/project.py
shapely_ext/space_explorer.py
shapely_ext/util.py
shapely_ext/geometry/__init__.py
shapely_ext/geometry/vector_2d.py
test/__init__.py
test/constant.py
test/space_explorer_test.py
test/test_angle.py
test/test_decompose.py
test/test_func.py
test/test_interpolate.py
test/test_mesh.py
test/test_project.py
test/test_util.py
test/util.py
shapely_ext-0.1.5.dist-info/LICENSE
shapely_ext-0.1.5.dist-info/METADATA
shapely_ext-0.1.5.dist-info/WHEEL
shapely_ext-0.1.5.dist-info/top_level.txt
shapely_ext-0.1.5.dist-info/RECORD
