Metadata-Version: 2.1
Name: shapely-ext
Version: 0.1.5
Summary: a shapely extension package providing magic function
Home-page: https://github.com/pyeprog/shapely_ext
Author: pd
Author-email: pyeprog@foxmail.com
License: UNKNOWN
Platform: UNKNOWN
Classifier: Programming Language :: Python :: 3
Classifier: License :: OSI Approved :: MIT License
Classifier: Operating System :: OS Independent
Requires-Python: >=3.6
Requires-Dist: Shapely (>=1.7.0)
Requires-Dist: scipy (>=1.4.1)
Requires-Dist: numpy (>=1.18.4)
